{"hotfix-http-throttling-v2-bug-1462906":{"name":"hotfix-http-throttling-v2-bug-1462906","branch":"hotfix","expired":false,"lastSeen":"2018-07-12T07:05:29.287Z","preferenceName":"network.http.throttle.version","preferenceValue":1,"preferenceType":"integer","previousPreferenceValue":2,"preferenceBranchType":"user","experimentType":"exp"},"pref-hotfix-tls-13-avast-rollback":{"name":"pref-hotfix-tls-13-avast-rollback","branch":"default","expired":false,"lastSeen":"2018-07-12T07:05:29.287Z","preferenceName":"security.tls.version.max","preferenceValue":3,"preferenceType":"integer","previousPreferenceValue":4,"preferenceBranchType":"default","experimentType":"exp"}}